CHANGES.txt
LICENSE.txt
MANIFEST.in
README.rst
distribute_setup.py
setup.py
performance_tools/__init__.py
performance_tools/context_managers.py
performance_tools.egg-info/PKG-INFO
performance_tools.egg-info/SOURCES.txt
performance_tools.egg-info/dependency_links.txt
performance_tools.egg-info/top_level.txt