Metadata-Version: 1.0
Name: performance-tools
Version: 0.2
Summary: Utilities for measuring application performance
Home-page: UNKNOWN
Author: Chris Adams
Author-email: chris@improbable.org
License: See LICENSE.txt
Platform: UNKNOWN
